spinach/__init__.py
spinach/const.py
spinach/engine.py
spinach/exc.py
spinach/job.py
spinach/queuey.py
spinach/signals.py
spinach/task.py
spinach/utils.py
spinach/worker.py
spinach/brokers/__init__.py
spinach/brokers/base.py
spinach/brokers/memory.py
spinach/brokers/redis.py
spinach/brokers/redis_scripts/__init__.py
spinach/brokers/redis_scripts/deregister.lua
spinach/brokers/redis_scripts/enqueue_job.lua
spinach/brokers/redis_scripts/enqueue_jobs_from_dead_broker.lua
spinach/brokers/redis_scripts/flush.lua
spinach/brokers/redis_scripts/get_jobs_from_queue.lua
spinach/brokers/redis_scripts/move_future_jobs.lua
spinach/brokers/redis_scripts/register_periodic_tasks.lua
spinach/brokers/redis_scripts/remove_job_from_running.lua
spinach/brokers/redis_scripts/set_concurrency_keys.lua
spinach/contrib/__init__.py
spinach/contrib/datadog.py
spinach/contrib/flask_spinach.py
spinach/contrib/sentry_sdk_spinach.py
spinach/contrib/spinachd/__init__.py
spinach/contrib/spinachd/apps.py
spinach/contrib/spinachd/mail.py
spinach/contrib/spinachd/settings.py
spinach/contrib/spinachd/signals.py
spinach/contrib/spinachd/tasks.py
spinach/contrib/spinachd/management/__init__.py
spinach/contrib/spinachd/management/commands/__init__.py
spinach/contrib/spinachd/management/commands/spinach.py
spinach-0.0.25.dist-info/LICENSE
spinach-0.0.25.dist-info/METADATA
spinach-0.0.25.dist-info/WHEEL
spinach-0.0.25.dist-info/top_level.txt
spinach-0.0.25.dist-info/RECORD
