Metadata-Version: 2.1
Name: spinach
Version: 0.0.25
Summary: Modern Redis task queue for Python 3
Home-page: https://github.com/NicolasLM/spinach
Author: Nicolas Le Manchet
Author-email: nicolas@lemanchet.fr
License: BSD 2-clause
Keywords: task queue jobs redis
Classifier: Development Status :: 4 - Beta
Classifier: Intended Audience :: Developers
Classifier: Topic :: Software Development :: Libraries
Classifier: Topic :: System :: Distributed Computing
Classifier: License :: OSI Approved :: BSD License
Classifier: Natural Language :: English
Classifier: Programming Language :: Python :: 3
Classifier: Programming Language :: Python :: 3 :: Only
Classifier: Programming Language :: Python :: 3.8
Classifier: Programming Language :: Python :: 3.9
Classifier: Programming Language :: Python :: 3.10
Classifier: Programming Language :: Python :: 3.11
Classifier: Programming Language :: Python :: 3.12
Classifier: Programming Language :: Python :: 3.13
License-File: LICENSE
Requires-Dist: redis
Requires-Dist: blinker
Provides-Extra: tests
Requires-Dist: pytest; extra == "tests"
Requires-Dist: pytest-cov; extra == "tests"
Requires-Dist: pytest-threadleak; extra == "tests"
Requires-Dist: pycodestyle; extra == "tests"
Requires-Dist: flask; extra == "tests"
Requires-Dist: django; extra == "tests"
